README.txt
setup.py
django_flatqueries.egg-info/PKG-INFO
django_flatqueries.egg-info/SOURCES.txt
django_flatqueries.egg-info/dependency_links.txt
django_flatqueries.egg-info/requires.txt
django_flatqueries.egg-info/top_level.txt
django_flatqueries.egg-info/zip-safe
sample_project/__init__.py
sample_project/demo_data.json
sample_project/manage.py
sample_project/settings.py
sample_project/urls.py
sample_project/flatqueries/__init__.py
sample_project/flatqueries/admin.py
sample_project/flatqueries/models.py
sample_project/flatqueries/tests.py
sample_project/flatqueries/urls.py
sample_project/flatqueries/views.py
sample_project/flatqueries/templates/flatqueries/run.html
sample_project/templates/base.html
sample_project/templates/flatpages/default.html