Metadata-Version: 1.0
Name: django-flatqueries
Version: 0.1
Summary: Flatpage-like SQL queries for Django.
Home-page: http://code.google.com/p/django-flatqueries/
Author: John Samuel Anderson
Author-email: john@andersoninnovative.com
License: MIT
Platform: UNKNOWN
